CSVWriter.py
bgcolours.py
pymmo.py
mongodbmanager-0.1.1.data/scripts/mm
tests/__init__.py
tests/test_pymmo.py
mongodbmanager-0.1.1.dist-info/METADATA
mongodbmanager-0.1.1.dist-info/WHEEL
mongodbmanager-0.1.1.dist-info/top_level.txt
mongodbmanager-0.1.1.dist-info/RECORD
