Metadata-Version: 2.1
Name: mongodbmanager
Version: 0.1.1
Summary: A simple utility for managing MongoDB Sharded Clusters
Home-page: https://github.com/rhysmeister/mmo
Author: Rhys Campbell
Author-email: rhys.james.campbell@googlemail.com
License: UNKNOWN
Platform: UNKNOWN
Classifier: Programming Language :: Python :: 3
Classifier: License :: Public Domain
Classifier: Operating System :: OS Independent
Requires-Python: >=3.5
Requires-Dist: pymongo
Requires-Dist: argparse
